esanom/README.md
esanom/__init__.py
esanom-3.0.3.749249.dist-info/METADATA
esanom-3.0.3.749249.dist-info/WHEEL
esanom-3.0.3.749249.dist-info/RECORD
