Metadata-Version: 2.1
Name: esanom
Version: 3.0.3.749249
Summary: ESANOM
Author: Zafar Iqbal
Author-email: zaf@sparc.space
Requires-Python: >=3.10,<3.13
Classifier: Programming Language :: Python :: 3
Classifier: Programming Language :: Python :: 3.10
Classifier: Programming Language :: Python :: 3.11
Classifier: Programming Language :: Python :: 3.12
Requires-Dist: cbor2 (==5.6.2)
Requires-Dist: flask (==3.0.2)
Requires-Dist: flask-compress (==1.14)
Requires-Dist: mysql-connector-python (==8.3.0)
Requires-Dist: networkx (==3.2.1)
Requires-Dist: psutil (==5.9.8)
Requires-Dist: requests (==2.31.0)
Requires-Dist: zstandard (==0.22.0)
